jetdnn/__init__.py
jetdnn/interpret.py
jetdnn/predict.py
jetdnn/visualise.py
tests/__init__.py
tests/test_data_manip.py
tests/test_interpret.py
tests/test_predict.py
tests/test_visualise.py
JETDNN-1.3.1.dist-info/LICENSE
JETDNN-1.3.1.dist-info/METADATA
JETDNN-1.3.1.dist-info/WHEEL
JETDNN-1.3.1.dist-info/top_level.txt
JETDNN-1.3.1.dist-info/RECORD
