Metadata-Version: 2.1
Name: JETDNN
Version: 1.3.1
Summary: JETDNN: a Python package using Deep Neural Networks (DNNs) to find H-mode plasma pedestal heights from multiple engineering parameters.
Home-page: https://github.com/quasoph/JETDNN
Author: S. Frankel, J. Simpson and E. Solano.
Author-email: s.frankel2@newcastle.ac.uk
License-File: LICENSE
